edfio/__init__.py
edfio/_header_field.py
edfio/_lazy_loading.py
edfio/edf.py
edfio/edf_annotations.py
edfio/edf_header.py
edfio/edf_signal.py
edfio/py.typed
edfio-0.4.12.dist-info/METADATA
edfio-0.4.12.dist-info/WHEEL
edfio-0.4.12.dist-info/licenses/LICENSE
edfio-0.4.12.dist-info/RECORD
