Metadata-Version: 2.4
Name: edfio
Version: 0.4.12
Summary: Read and write EDF/EDF+C/BDF/BDF+C files.
Project-URL: repository, https://github.com/the-siesta-group/edfio
Project-URL: documentation, https://edfio.readthedocs.io
Author-email: The Siesta Group <opensource@thesiestagroup.com>
License: Apache-2.0
License-File: LICENSE
Classifier: License :: OSI Approved :: Apache Software License
Classifier: Programming Language :: Python :: 3
Classifier: Programming Language :: Python :: 3.9
Classifier: Programming Language :: Python :: 3.10
Classifier: Programming Language :: Python :: 3.11
Classifier: Programming Language :: Python :: 3.12
Classifier: Programming Language :: Python :: 3.13
Classifier: Programming Language :: Python :: 3.14
Requires-Python: >=3.9
Requires-Dist: numpy>=1.22.0
Requires-Dist: typing-extensions>=4.0.0; python_version < '3.11'
